KerasZhongwenWendang/README.md
KerasZhongwenWendang/__init__.py
KerasZhongwenWendang/__main__.py
KerasZhongwenWendang/file.epub
KerasZhongwenWendang/index.html
KerasZhongwenWendang/css/__init__.py
KerasZhongwenWendang/css/annotations.css
KerasZhongwenWendang/css/main.css
KerasZhongwenWendang/css/normalize.css
KerasZhongwenWendang/css/popup.css
KerasZhongwenWendang/font/__init__.py
KerasZhongwenWendang/font/fontello.eot
KerasZhongwenWendang/font/fontello.svg
KerasZhongwenWendang/font/fontello.ttf
KerasZhongwenWendang/font/fontello.woff
KerasZhongwenWendang/img/__init__.py
KerasZhongwenWendang/img/annotator-glyph-sprite.png
KerasZhongwenWendang/img/annotator-icon-sprite.png
KerasZhongwenWendang/img/apple-touch-icon.png
KerasZhongwenWendang/img/cancelfullscreen.png
KerasZhongwenWendang/img/close.png
KerasZhongwenWendang/img/fullscreen.png
KerasZhongwenWendang/img/loader.gif
KerasZhongwenWendang/img/menu-icon.png
KerasZhongwenWendang/img/save.png
KerasZhongwenWendang/img/saved.png
KerasZhongwenWendang/img/settings-s.png
KerasZhongwenWendang/img/settings.png
KerasZhongwenWendang/img/star.png
KerasZhongwenWendang/js/__init__.py
KerasZhongwenWendang/js/epub.js
KerasZhongwenWendang/js/epub.min.js
KerasZhongwenWendang/js/epub.min.map
KerasZhongwenWendang/js/hooks.min.js
KerasZhongwenWendang/js/hooks.min.map
KerasZhongwenWendang/js/reader.js
KerasZhongwenWendang/js/reader.js.map
KerasZhongwenWendang/js/reader.min.js
KerasZhongwenWendang/js/reader.min.map
KerasZhongwenWendang/js/hooks/__init__.py
KerasZhongwenWendang/js/hooks/extensions/__init__.py
KerasZhongwenWendang/js/hooks/extensions/highlight.js
KerasZhongwenWendang/js/libs/__init__.py
KerasZhongwenWendang/js/libs/jquery.min.js
KerasZhongwenWendang/js/libs/localforage.min.js
KerasZhongwenWendang/js/libs/screenfull.js
KerasZhongwenWendang/js/libs/screenfull.min.js
KerasZhongwenWendang/js/libs/zip.min.js
KerasZhongwenWendang/js/plugins/__init__.py
KerasZhongwenWendang/js/plugins/hypothesis.js
keras_zhongwen_wendang-2024.3.2.0.dist-info/METADATA
keras_zhongwen_wendang-2024.3.2.0.dist-info/WHEEL
keras_zhongwen_wendang-2024.3.2.0.dist-info/entry_points.txt
keras_zhongwen_wendang-2024.3.2.0.dist-info/top_level.txt
keras_zhongwen_wendang-2024.3.2.0.dist-info/RECORD
